SEBAL/Excel_SEBAL_v3_4_4.xlsx
SEBAL/Run_SEBAL.py
SEBAL/__init__.py
SEBAL/pySEBAL/__init__.py
SEBAL/pySEBAL/pySEBAL_code.py
SEBAL/pySEBAL/pySEBAL_code_EE.py
SEBAL/pySEBAL/pySEBAL_code_new_gebruik_deze_bij_uitzondering.py
SEBAL/pySEBAL/pySEBAL_code_old.py
SEBAL/pySEBAL/pySEBAL_input_LANDSAT.py
SEBAL/pySEBAL/pySEBAL_input_MODIS.py
SEBAL/pySEBAL/pySEBAL_input_PROBAV_VIIRS.py
SEBAL/pySEBAL/pySEBAL_input_USER.py
SEBAL-3.4.4.3.dist-info/LICENSE
SEBAL-3.4.4.3.dist-info/METADATA
SEBAL-3.4.4.3.dist-info/WHEEL
SEBAL-3.4.4.3.dist-info/top_level.txt
SEBAL-3.4.4.3.dist-info/RECORD
