Metadata-Version: 2.1
Name: SEBAL
Version: 3.4.4.3
Summary: Python module for Surface Energy Balance Algorithm for Land
Home-page: https://github.com/TimHessels/SEBAL
Author: Tim Hessels
Author-email: timhessels@hotmail.com
License: UNKNOWN
Platform: UNKNOWN
Classifier: Programming Language :: Python :: 2
Classifier: Programming Language :: Python :: 3
Classifier: License :: OSI Approved :: Apache Software License
Classifier: Operating System :: OS Independent
Requires-Dist: Pillow
Requires-Dist: h5py
Requires-Dist: lxml
Requires-Dist: netCDF4
Requires-Dist: openpyxl
Requires-Dist: numpy
Requires-Dist: pandas
Requires-Dist: scipy
Requires-Dist: pyproj
Requires-Dist: joblib
